decentra_vision/__init__.py
decentra_vision/constants.py
decentra_vision/draw_utils.py
decentra_vision/geometry_methods.py
decentra_vision/ver.py
decentra_vision-2.0.0.dist-info/METADATA
decentra_vision-2.0.0.dist-info/WHEEL
decentra_vision-2.0.0.dist-info/licenses/LICENSE
decentra_vision-2.0.0.dist-info/RECORD
